pyaidoop-graphql-client/__init__.py
pyaidoop-graphql-client/api.py
pyaidoop-graphql-client/graphql/__init__.py
pyaidoop-graphql-client/graphql/decorator.py
pyaidoop-graphql-client/graphql/queries.py
pyaidoop-graphql-client/graphql/queries_robot_api.py
pyaidoop-graphql-client/graphql/queries_robot_arm.py
pyaidoop-graphql-client/graphql/queries_trackable_object.py
pyaidoop-graphql-client/graphql/queries_tracking_camera.py
pyaidoop-graphql-client/graphql/queries_tracking_workspace.py
pyaidoop_graphql_client/__init__.py
pyaidoop_graphql_client/api.py
pyaidoop_graphql_client/graphql/__init__.py
pyaidoop_graphql_client/graphql/decorator.py
pyaidoop_graphql_client/graphql/queries.py
pyaidoop_graphql_client/graphql/queries_robot_api.py
pyaidoop_graphql_client/graphql/queries_robot_arm.py
pyaidoop_graphql_client/graphql/queries_trackable_object.py
pyaidoop_graphql_client/graphql/queries_tracking_camera.py
pyaidoop_graphql_client/graphql/queries_tracking_workspace.py
pyaidoop_graphql_client-0.4.0.dist-info/LICENSE
pyaidoop_graphql_client-0.4.0.dist-info/METADATA
pyaidoop_graphql_client-0.4.0.dist-info/WHEEL
pyaidoop_graphql_client-0.4.0.dist-info/top_level.txt
pyaidoop_graphql_client-0.4.0.dist-info/RECORD
