Metadata-Version: 2.1
Name: pyaidoop-graphql-client
Version: 0.4.0
Summary: A graphql communication library for AIdoop web-based application platform
Home-page: https://github.com/aidoop/vision-client-python.git
Author: 
Author-email: 
License: MIT
Keywords: cooperative robot,web-based application,grpahql
Platform: UNKNOWN
Classifier: Intended Audience :: Developers
Classifier: License :: OSI Approved :: MIT License
Classifier: Natural Language :: English
Classifier: Operating System :: OS Independent
Classifier: Programming Language :: Python :: 3.6
Classifier: Programming Language :: Python :: 3.7
Classifier: Programming Language :: Python :: 3.8
Classifier: Topic :: Software Development :: Libraries :: Python Modules
License-File: LICENSE
Requires-Dist: requests
Requires-Dist: gql
